shopyo_page/__init__.py
shopyo_page/forms.py
shopyo_page/helpers.py
shopyo_page/info.json
shopyo_page/models.py
shopyo_page/view.py
shopyo_page/templates/shopyo_page/all_pages.html
shopyo_page/templates/shopyo_page/dashboard.html
shopyo_page/templates/shopyo_page/dashboard_edit.html
shopyo_page/templates/shopyo_page/revisions.html
shopyo_page/templates/shopyo_page/view_page.html
shopyo_page/templates/shopyo_page/view_page_dashboard.html
shopyo_page/templates/shopyo_page/blocks/sidebar.html
shopyo_page-1.3.0.dist-info/METADATA
shopyo_page-1.3.0.dist-info/WHEEL
shopyo_page-1.3.0.dist-info/top_level.txt
shopyo_page-1.3.0.dist-info/RECORD
